{
  "v": "5.5.2", "fr": 30, "ip": 0, "op": 45, "w": 24, "h": 24, "nm": "alert-octagon", "ddd": 0, "assets": [],
  "layers": [
	{
	  "ddd": 0, "ind": 1, "ty": 4, "nm": "alert-octagon", "sr": 1, "ks": {
	  "o": {"a": 0, "k": 100, "ix": 11}, "r": {"a": 0, "k": 0, "ix": 10}, "p": {"a": 0, "k": [12, 12, 0], "ix": 2},
	  "a": {"a": 0, "k": [12, 12, 0], "ix": 1}, "s": {"a": 0, "k": [100, 100, 100], "ix": 6}
	}, "ao": 0, "shapes": [
	  {
		"ty": "gr", "it": [
		{
		  "ind": 0, "ty": "sh", "ix": 1,
		  "ks": {"a": 0, "k": {"i": [[0, 0]], "o": [[0, 0]], "v": [[12, 16]], "c": true}, "ix": 2}, "nm": "Path 1",
		  "mn": "ADBE Vector Shape - Group", "hd": false
		}, {
		  "ty": "st", "c": {"a": 0, "k": [0, 0, 0, 1], "ix": 3}, "o": {"a": 0, "k": 100, "ix": 4},
		  "w": {"a": 0, "k": 2, "ix": 5}, "lc": 2, "lj": 2, "bm": 0, "nm": "Stroke 1",
		  "mn": "ADBE Vector Graphic - Stroke", "hd": false
		}, {
		  "ty": "tr", "p": {"a": 0, "k": [0, 0], "ix": 2}, "a": {"a": 0, "k": [0, 0], "ix": 1},
		  "s": {"a": 0, "k": [100, 100], "ix": 3}, "r": {"a": 0, "k": 0, "ix": 6}, "o": {"a": 0, "k": 100, "ix": 7},
		  "sk": {"a": 0, "k": 0, "ix": 4}, "sa": {"a": 0, "k": 0, "ix": 5}, "nm": "Transform"
		}
	  ], "nm": "dot", "np": 2, "cix": 2, "bm": 0, "ix": 1, "mn": "ADBE Vector Group", "hd": false
	  }, {
		"ty": "gr", "it": [
		  {
			"ind": 0, "ty": "sh", "ix": 1, "ks": {
			"a": 0, "k": {"i": [[0, 0], [0, 0]], "o": [[0, 0], [0, 0]], "v": [[12, 8], [12, 12]], "c": false}, "ix": 2
		  }, "nm": "Path 1", "mn": "ADBE Vector Shape - Group", "hd": false
		  }, {
			"ty": "st", "c": {"a": 0, "k": [0, 0, 0, 1], "ix": 3}, "o": {"a": 0, "k": 100, "ix": 4},
			"w": {"a": 0, "k": 2, "ix": 5}, "lc": 2, "lj": 2, "bm": 0, "nm": "Stroke 1",
			"mn": "ADBE Vector Graphic - Stroke", "hd": false
		  }, {
			"ty": "tr", "p": {"a": 0, "k": [0, 0], "ix": 2}, "a": {"a": 0, "k": [0, 0], "ix": 1},
			"s": {"a": 0, "k": [100, 100], "ix": 3}, "r": {"a": 0, "k": 0, "ix": 6}, "o": {"a": 0, "k": 100, "ix": 7},
			"sk": {"a": 0, "k": 0, "ix": 4}, "sa": {"a": 0, "k": 0, "ix": 5}, "nm": "Transform"
		  }
		], "nm": "exclamation", "np": 2, "cix": 2, "bm": 0, "ix": 2, "mn": "ADBE Vector Group", "hd": false
	  }, {
		"ty": "gr", "it": [
		  {
			"ind": 0, "ty": "sh", "ix": 1, "ks": {
			"a": 0, "k": {
			  "i": [[0, 0], [0, 0], [0, 0], [0, 0], [0, 0], [0, 0], [0, 0], [0, 0]],
			  "o": [[0, 0], [0, 0], [0, 0], [0, 0], [0, 0], [0, 0], [0, 0], [0, 0]], "v": [
				[-4.14, -10], [4.14, -10], [10, -4.14], [10, 4.14], [4.14, 10], [-4.14, 10], [-10, 4.14], [-10, -4.14]
			  ], "c": true
			}, "ix": 2
		  }, "nm": "Path 1", "mn": "ADBE Vector Shape - Group", "hd": false
		  }, {
			"ty": "st", "c": {"a": 0, "k": [0, 0, 0, 1], "ix": 3}, "o": {"a": 0, "k": 100, "ix": 4}, "w": {
			  "a": 1, "k": [
				{"i": {"x": [0.833], "y": [0.833]}, "o": {"x": [0.333], "y": [0]}, "t": 35, "s": [1]},
				{"t": 45, "s": [2]}
			  ], "ix": 5
			}, "lc": 2, "lj": 2, "bm": 0, "nm": "Stroke 1", "mn": "ADBE Vector Graphic - Stroke", "hd": false
		  }, {
			"ty": "tr", "p": {"a": 0, "k": [12, 12], "ix": 2}, "a": {"a": 0, "k": [0, 0], "ix": 1}, "s": {
			  "a": 1, "k": [
				{
				  "i": {"x": [0.833, 0.833], "y": [0.833, 0.833]}, "o": {"x": [0.167, 0.167], "y": [0.167, 0.167]},
				  "t": 35, "s": [50, 50]
				}, {"t": 45, "s": [85, 85]}
			  ], "ix": 3
			}, "r": {"a": 0, "k": 0, "ix": 6}, "o": {
			  "a": 1, "k": [
				{"i": {"x": [0.667], "y": [1]}, "o": {"x": [0.333], "y": [0]}, "t": 35, "s": [0]}, {"t": 45, "s": [100]}
			  ], "ix": 7
			}, "sk": {"a": 0, "k": 0, "ix": 4}, "sa": {"a": 0, "k": 0, "ix": 5}, "nm": "Transform"
		  }
		], "nm": "octagon 2", "np": 2, "cix": 2, "bm": 0, "ix": 3, "mn": "ADBE Vector Group", "hd": false
	  }, {
		"ty": "gr", "it": [
		  {
			"ind": 0, "ty": "sh", "ix": 1, "ks": {
			"a": 0, "k": {
			  "i": [[0, 0], [0, 0], [0, 0], [0, 0], [0, 0], [0, 0], [0, 0], [0, 0]],
			  "o": [[0, 0], [0, 0], [0, 0], [0, 0], [0, 0], [0, 0], [0, 0], [0, 0]], "v": [
				[-4.14, -10], [4.14, -10], [10, -4.14], [10, 4.14], [4.14, 10], [-4.14, 10], [-10, 4.14], [-10, -4.14]
			  ], "c": true
			}, "ix": 2
		  }, "nm": "Path 1", "mn": "ADBE Vector Shape - Group", "hd": false
		  }, {
			"ty": "st", "c": {"a": 0, "k": [0, 0, 0, 1], "ix": 3}, "o": {"a": 0, "k": 100, "ix": 4},
			"w": {"a": 0, "k": 2, "ix": 5}, "lc": 2, "lj": 2, "bm": 0, "nm": "Stroke 1",
			"mn": "ADBE Vector Graphic - Stroke", "hd": false
		  }, {
			"ty": "tr", "p": {"a": 0, "k": [12, 12], "ix": 2}, "a": {"a": 0, "k": [0, 0], "ix": 1}, "s": {
			  "a": 1, "k": [
				{
				  "i": {"x": [0.833, 0.833], "y": [0.833, 0.833]}, "o": {"x": [0.167, 0.167], "y": [0.167, 0.167]},
				  "t": 0, "s": [85, 85]
				}, {"t": 42, "s": [104, 104]}
			  ], "ix": 3
			}, "r": {"a": 0, "k": 0, "ix": 6}, "o": {
			  "a": 1, "k": [
				{"i": {"x": [0.833], "y": [0.833]}, "o": {"x": [0.167], "y": [0.167]}, "t": 0, "s": [100]},
				{"t": 42, "s": [0]}
			  ], "ix": 7
			}, "sk": {"a": 0, "k": 0, "ix": 4}, "sa": {"a": 0, "k": 0, "ix": 5}, "nm": "Transform"
		  }
		], "nm": "octagon", "np": 2, "cix": 2, "bm": 0, "ix": 4, "mn": "ADBE Vector Group", "hd": false
	  }
	], "ip": 0, "op": 45, "st": 0, "bm": 0
	}
  ], "markers": []
}